metdley/__init__.py
metdley/auth.py
metdley/client.py
metdley/processing.py
metdley/search.py
metdley/status.py
Metdley-0.1.2.post2.dist-info/METADATA
Metdley-0.1.2.post2.dist-info/WHEEL
Metdley-0.1.2.post2.dist-info/top_level.txt
Metdley-0.1.2.post2.dist-info/RECORD
